LICENSE
MANIFEST.in
README.rst
setup.py
pyscrum/__init__.py
pyscrum/core.py
pyscrum/loaders.py
pyscrum.egg-info/PKG-INFO
pyscrum.egg-info/SOURCES.txt
pyscrum.egg-info/dependency_links.txt
pyscrum.egg-info/entry_points.txt
pyscrum.egg-info/requires.txt
pyscrum.egg-info/top_level.txt
pyscrum/templates/base.html
pyscrum/templates/board.html
pyscrum/templates/burndown.html
pyscrum/templates/partial/_storycard.html
pyscrum/templates/partial/_task.html
pyscrum/tools/__init__.py
pyscrum/tools/mkboard.py
pyscrum/tools/mkburndown.py