Metadata-Version: 1.0
Name: pyscrum
Version: 0.1
Summary: Generate scrum boards and charts from .rst task logs.
Home-page: http://github.com/alexmorozov/pyscrum
Author: Alex Morozov
Author-email: inductor2000@mail.ru
License: GPLv3
Platform: UNKNOWN
